tenta-0.1.5.dist-info/METADATA
tenta-0.1.5.dist-info/WHEEL
tenta-0.1.5.dist-info/licenses/LICENSE
tenta/__init__.py
tenta/client.py
tenta/py.typed
tenta/types.py
tenta-0.1.5.dist-info/RECORD
