Metadata-Version: 2.1
Name: tenta
Version: 0.1.5
Summary: Python client library for Tenta, a sensor network management tool
Author-Email: Moritz Makowski <moritz.makowski@tum.de>
License: MIT
Classifier: License :: OSI Approved :: MIT License
Classifier: Programming Language :: Python :: 3
Classifier: Programming Language :: Python :: 3.8
Classifier: Programming Language :: Python :: 3.9
Classifier: Programming Language :: Python :: 3.10
Classifier: Programming Language :: Python :: 3.11
Classifier: Programming Language :: Python :: 3.12
Project-URL: Repository, https://github.com/tum-esm/tenta-client
Project-URL: Documentation, https://tenta-python-client.netlify.app/
Requires-Python: <4.0,>=3.8
Requires-Dist: paho-mqtt>=2.1.0
Requires-Dist: mypy>=1.11.1; extra == "dev"
Requires-Dist: pytest>=8.3.2; extra == "dev"
Requires-Dist: pytest-cov>=5.0.0; extra == "dev"
Requires-Dist: pytest-order>=1.2.1; extra == "dev"
Requires-Dist: pydoc-markdown>=4.8.2; extra == "dev"
Requires-Dist: yapf>=0.40.2; extra == "dev"
Provides-Extra: dev
